{
  "X": [
    "Jessica Chen Data Scientist | Machine Learning Engineer Email: jessica.chen@example.com | Phone: (999) 000-1111 | LinkedIn: linkedin.com/in/jessicachen | GitHub: github.com/jessicachen-ds Professional Profile Highly analytical and innovative Data Scientist with 6 years of experience specializing in machine learning, statistical modeling, and big data analysis. Proven ability to translate complex data into actionable insights and build robust predictive models that drive business value. Proficient in Python, R, and various machine learning frameworks, with a strong background in cloud platforms and MLOps. Seeking to apply advanced analytical skills to solve challenging problems in a data-driven organization. Core Competencies e Machine Learning: Supervised/Unsupervised Learning, Deep Learning, NLP, Time Series Analysis, Model Evaluation, Hyperparameter Tuning Programming: Python (Scikit-learn, TensorFlow, Keras, PyTorch, Pandas, NumPy, SciPy), R, SQL Data Analysis: Statistical Modeling, A/B Testing, Hypothesis Testing, Data Visualization (Matplotlib, Seaborn, Plotly, Tableau) Big Data & Cloud: Apache Spark, Hadoop, AWS (S3, EC2, SageMaker, Lambda), Google Cloud Platform (BigQuery, Al Platform) Tools & Methodologies: Git, Docker, Jupyter Notebooks, MLflow, Agile, Data Storytelling Professional Experience Lead Data Scientist Data Insights Corp. | Seattle, WA | January 2021 — Present e Ledateam of 4 data scientists in developing and deploying machine learning models for fraud detection, resulting in a 25% reduction in false positives and $1.5M annual savings. Designed and implemented a customer lifetime value (CLTV) prediction model using advanced regression techniques, improving marketing campaign targeting efficiency by 18%. Developed and maintained end-to-end ML pipelines on AWS SageMaker, automating data ingestion, model training, and deployment processes.\nCollaborated with engineering teams to integrate ML models into production systems, ensuring scalability and reliability. Presented complex analytical findings to executive stakeholders, influencing strategic business decisions. Data Scientist Tech Innovations Group | San Francisco, CA | August 2018 — December 2020 e Built and validated predictive models for customer churn using Python and Scikit- learn, leading to a 10% increase in customer retention. Performed extensive exploratory data analysis (EDA) on large datasets to identify key trends and anomalies. Developed interactive dashboards in Tableau to visualize key business metrics and model performance. Contributed to the design of A/B tests and analyzed results to optimize product features. Junior Data Analyst Analytics Solutions LLC | San Jose, CA | June 2017 — July 2018 e Cleaned, transformed, and analyzed structured and unstructured data using SQL and Python. e Generated weekly reports on sales performance and market trends. Key Projects Real-time Anomaly Detection System Data Insights Corp. | 2023 e Objective: Develop a real-time system to detect anomalies in financial transactions. Technologies: Python, Apache Flink, Kafka, TensorFlow, AWS Kinesis. Outcome: Achieved 98% detection accuracy with sub-second latency, significantly reducing fraudulent activities. Personalized Recommendation Engine Personal Project | 2022 e Objective: Build a content recommendation engine based on user behavior. e Technologies: Python, PyTorch, Collaborative Filtering, AWS EC2.\ne Outcome: Implemented a proof-of-concept that demonstrated improved recommendation relevance compared to baseline methods. Education Master of Science in Data Science University of California, Berkeley | Berkeley, CA | 2016 — 2017 e Thesis: \"Deep Learning for Natural Language Understanding in Customer Support.\" Bachelor of Science in Statistics University of Washington | Seattle, WA | 2012 — 2016 e Minor: Computer Science e Honors: Magna Cum Laude Professional Development & Certifications e AWS Certified Machine Learning — Specialty (2022) e Google Cloud Professional Data Engineer (2021) e Coursera Specialization: Deep Learning (Andrew Ng) — Completed 2020 Community Involvement Data Science Mentor Local Tech Hub | Seattle, WA | 2021 — Present e Provided guidance and mentorship to aspiring data scientists on career paths and technical skills. e Led workshops on introductory Python for data analysis. Publications Chen, J., & Smith, A. (2023). \"Improving Fraud Detection with Graph Neural Networks.\" Journal of Applied Data Science, 10(2), 123-135. \"The Role of Explainable Al in Financial Modeling\" — Guest Lecture, University of Washington (2024)\n"
  ],
  "y": [
    {
      "personal_info": {
        "name": "Jessica Chen",
        "email": "jessica.chen@example.com",
        "phone": "(999) 000-1111",
        "location": null,
        "linkedin": "linkedin.com/in/jessicachen"
      },
      "professional_summary": {
        "headline": "Data Scientist | Machine Learning Engineer",
        "summary": "Highly analytical and innovative Data Scientist with 6 years of experience specializing in machine learning, statistical modeling, and big data analysis. Proven ability to translate complex data into actionable insights and build robust predictive models that drive business value. Proficient in Python, R, and various machine learning frameworks, with a strong background in cloud platforms and MLOps. Seeking to apply advanced analytical skills to solve challenging problems in a data-driven organization.",
        "total_experience_years": 6,
        "career_level": null
      },
      "work_experience": [
        {
          "title": "Lead Data Scientist",
          "company": "Data Insights Corp.",
          "start_date": "January 2021",
          "end_date": "Present",
          "duration_months": null,
          "responsibilities": null,
          "achievements": [
            "Ledateam of 4 data scientists in developing and deploying machine learning models for fraud detection, resulting in a 25% reduction in false positives and $1.5M annual savings.",
            "Designed and implemented a customer lifetime value (CLTV) prediction model using advanced regression techniques, improving marketing campaign targeting efficiency by 18%.",
            "Developed and maintained end-to-end ML pipelines on AWS SageMaker, automating data ingestion, model training, and deployment processes.",
            "Collaborated with engineering teams to integrate ML models into production systems, ensuring scalability and reliability.",
            "Presented complex analytical findings to executive stakeholders, influencing strategic business decisions."
          ],
          "technologies_used": null
        },
        {
          "title": "Data Scientist",
          "company": "Tech Innovations Group",
          "start_date": "August 2018",
          "end_date": "December 2020",
          "duration_months": null,
          "responsibilities": null,
          "achievements": [
            "Built and validated predictive models for customer churn using Python and Scikit- learn, leading to a 10% increase in customer retention.",
            "Performed extensive exploratory data analysis (EDA) on large datasets to identify key trends and anomalies.",
            "Developed interactive dashboards in Tableau to visualize key business metrics and model performance.",
            "Contributed to the design of A/B tests and analyzed results to optimize product features."
          ],
          "technologies_used": null
        },
        {
          "title": "Junior Data Analyst",
          "company": "Analytics Solutions LLC",
          "start_date": "June 2017",
          "end_date": "July 2018",
          "duration_months": null,
          "responsibilities": null,
          "achievements": [
            "Cleaned, transformed, and analyzed structured and unstructured data using SQL and Python.",
            "Generated weekly reports on sales performance and market trends."
          ],
          "technologies_used": null
        }
      ],
      "skills": {
        "technical": [
          "Machine Learning",
          "Supervised/Unsupervised Learning",
          "Deep Learning",
          "NLP",
          "Time Series Analysis",
          "Model Evaluation",
          "Hyperparameter Tuning",
          "Python",
          "Scikit-learn",
          "TensorFlow",
          "Keras",
          "PyTorch",
          "Pandas",
          "NumPy",
          "SciPy",
          "R",
          "SQL",
          "Data Analysis",
          "Statistical Modeling",
          "A/B Testing",
          "Hypothesis Testing",
          "Data Visualization",
          "Matplotlib",
          "Seaborn",
          "Plotly",
          "Tableau",
          "Big Data & Cloud",
          "Apache Spark",
          "Hadoop",
          "AWS",
          "S3",
          "EC2",
          "SageMaker",
          "Lambda",
          "Google Cloud Platform",
          "BigQuery",
          "Al Platform",
          "Tools & Methodologies",
          "Git",
          "Docker",
          "Jupyter Notebooks",
          "MLflow"
        ],
        "soft": [
          "Agile",
          "Data Storytelling"
        ],
        "certifications": [
          "AWS Certified Machine Learning — Specialty (2022)",
          "Google Cloud Professional Data Engineer (2021)",
          "Coursera Specialization: Deep Learning (Andrew Ng) — Completed 2020"
        ]
      },
      "education": [
        {
          "degree": "Master of Science in Data Science",
          "institution": "University of California, Berkeley",
          "graduation_year": 2017,
          "gpa": null
        },
        {
          "degree": "Bachelor of Science in Statistics",
          "institution": "University of Washington",
          "graduation_year": 2016,
          "gpa": null
        }
      ],
      "keywords": [
        "Machine Learning",
        "Data Scientist",
        "Python",
        "R",
        "SQL",
        "AWS",
        "Google Cloud Platform",
        "Big Data",
        "Data Analysis",
        "Deep Learning",
        "NLP",
        "Apache Spark",
        "Hadoop",
        "Tableau",
        "TensorFlow",
        "PyTorch",
        "Scikit-learn"
      ]
    }
  ]
}